{"yuidev": {"status": {"charisma": 0, "max_hp": 0, "wisdom": 0, "class": "healer", "intelligent": 0, "hp": -9, "ac": 0, "res_parrelize": 0, "res_magicstaff": 0, "level": 1, "agillity": 0, "res_breath": 0, "res_poison": 0, "res_sturn": 0, "health": 0, "res_magicstic": 0, "res_death": 0, "res_magicspell": 0, "strength": 0}, "realuser": "yuidev", "charname": "horo", "values": "sun", "skills": [{"smash": 0}, {"block": 0}], "actions": [{"move": 0}]}, "c": {"status": {"charisma": 0, "max_hp": 0, "wisdom": 0, "class": "c", "intelligent": 0, "hp": 0, "ac": 0, "res_parrelize": 0, "res_magicstaff": 0, "level": 1, "agillity": 0, "res_breath": 0, "res_poison": 0, "res_sturn": 0, "health": 0, "res_magicstic": 0, "res_death": 0, "res_magicspell": 0, "strength": 0}, "realuser": "c", "charname": "c", "values": "c", "skills": [{"basic": 0}, {"testmod": 0}], "actions": [{"move": 0}]}, "a": {"status": {"charisma": 0, "max_hp": 100, "wisdom": 0, "class": "a", "intelligent": 0, "hp": 0, "ac": 0, "res_parrelize": 0, "res_magicstaff": 0, "level": 1, "agillity": 0, "res_breath": 0, "res_poison": 0, "res_sturn": 0, "health": 0, "res_magicstic": 0, "res_death": 0, "res_magicspell": 0, "strength": 0}, "realuser": "a", "charname": "a", "values": "a", "skills": [{"basic": 0}, {"testmod": 0}], "actions": [{"move": 0}]}}